pantrypal/__init__.py
pantrypal/constants.py
pantrypal/ingredient.py
pantrypal/mealplan.py
pantrypal/recipe.py
pantrypal/tgbot.py
pantrypal-0.0.1.dist-info/METADATA
pantrypal-0.0.1.dist-info/WHEEL
pantrypal-0.0.1.dist-info/top_level.txt
pantrypal-0.0.1.dist-info/RECORD
